{"stat.chestOpened":2,"stat.useItem.minecraft.bow":1,"stat.walkOneCm":208196,"achievement.openInventory":20,"stat.useItem.minecraft.stone":1,"stat.useItem.minecraft.jungle_fence":1,"stat.leaveGame":1,"stat.damageTaken":102027,"stat.useItem.minecraft.skull":31,"stat.useItem.minecraft.diamond_sword":5,"stat.flyOneCm":97472,"stat.deaths":15,"stat.mineBlock.minecraft.stained_glass":33,"stat.drop":2,"stat.jump":389,"stat.playOneMinute":37784,"stat.fallOneCm":6850,"stat.useItem.minecraft.wooden_sword":12,"stat.climbOneCm":624,"stat.useItem.minecraft.sea_lantern":8,"stat.useItem.minecraft.stone_sword":2,"stat.damageDealt":945,"stat.crouchOneCm":5280,"stat.useItem.minecraft.wool":44,"stat.mineBlock.minecraft.wool":8,"stat.useItem.minecraft.coal_block":81,"stat.enderchestOpened":2,"stat.timeSinceDeath":166,"stat.useItem.minecraft.dirt":19,"stat.sprintOneCm":78604,"stat.mineBlock.minecraft.dirt":3,"achievement.exploreAllBiomes":{"value":0,"progress":["Ice Plains","Plains"]}}